opti/__init__.py
opti/constraint.py
opti/metric.py
opti/model.py
opti/objective.py
opti/parameter.py
opti/problem.py
opti/problems/__init__.py
opti/problems/cbo_benchmarks.py
opti/problems/datasets.py
opti/problems/detergent.py
opti/problems/mixed.py
opti/problems/multi.py
opti/problems/single.py
opti/problems/univariate.py
opti/problems/zdt.py
opti/problems/data/alkox.csv
opti/problems/data/baumgartner_aniline.csv
opti/problems/data/baumgartner_benzamide.csv
opti/problems/data/benzylation.csv
opti/problems/data/cake.csv
opti/problems/data/fullerenes.csv
opti/problems/data/hplc.csv
opti/problems/data/photodegradation.csv
opti/problems/data/reizman_suzuki1.csv
opti/problems/data/reizman_suzuki2.csv
opti/problems/data/reizman_suzuki3.csv
opti/problems/data/reizman_suzuki4.csv
opti/problems/data/snar.csv
opti/problems/data/suzuki.csv
opti/sampling/__init__.py
opti/sampling/base.py
opti/sampling/polytope.py
opti/sampling/simplex.py
opti/sampling/sphere.py
opti/tools/__init__.py
opti/tools/modde.py
opti/tools/noisify.py
opti/tools/reduce.py
opti/tools/sanitize.py
test/__init__.py
test/test_constraint.py
test/test_docs.py
test/test_metric.py
test/test_modde.py
test/test_model.py
test/test_noisify.py
test/test_objective.py
test/test_parameter.py
test/test_problem.py
test/test_problems.py
test/test_reduce.py
test/test_sampling.py
test/test_sanitize.py
mopti-0.10.10.dist-info/LICENSE
mopti-0.10.10.dist-info/METADATA
mopti-0.10.10.dist-info/WHEEL
mopti-0.10.10.dist-info/top_level.txt
mopti-0.10.10.dist-info/RECORD
