Metadata-Version: 2.1
Name: mopti
Version: 0.10.10
Summary: Tools for experimental design and multi-objective optimization
Home-page: https://github.com/basf/mopti
Author: BASF SE
License: BSD-3
Keywords: Bayesian optimization,Multi-objective optimization,Experimental design
Classifier: Development Status :: 4 - Beta
Classifier: Programming Language :: Python :: 3 :: Only
Classifier: License :: OSI Approved :: BSD License
Classifier: Topic :: Scientific/Engineering
Classifier: Intended Audience :: Science/Research
Classifier: Intended Audience :: Developers
Requires-Python: >=3.7
License-File: LICENSE
Requires-Dist: numpy
Requires-Dist: pandas
Requires-Dist: scipy (>=1.7)
Provides-Extra: docs
Requires-Dist: mkdocs ; extra == 'docs'
Requires-Dist: mkdocs-material ; extra == 'docs'
Requires-Dist: mkdocstrings (>=0.18) ; extra == 'docs'
Requires-Dist: mkdocstrings-python-legacy ; extra == 'docs'
Provides-Extra: tests
Requires-Dist: pytest ; extra == 'tests'
Requires-Dist: scikit-learn ; extra == 'tests'
